reconPy.py
reconpy-1.0.5.dist-info/METADATA
reconpy-1.0.5.dist-info/WHEEL
reconpy-1.0.5.dist-info/RECORD
