Metadata-Version: 2.4
Name: reconPy
Version: 1.0.5
Summary: reconPy is a powerful yet user-friendly data reconciliation engine dessigned to compare records across two dataframes. It's particularly well-suited for financial sector applications, including: asset management firms, banks, brokers-dealers and hedge funds.
Project-URL: Homepage, https://github.com/Meowfit/reconPy
Author: KT
Classifier: License :: OSI Approved :: MIT License
Classifier: Operating System :: OS Independent
Classifier: Programming Language :: Python :: 3
Requires-Python: >=3.8
Requires-Dist: fuzzywuzzy
Requires-Dist: numpy
Requires-Dist: pandas
